aria_gen2_pilot_dataset/__init__.py
aria_gen2_pilot_dataset/data_provider/aria_gen2_pilot_data_file_keys.py
aria_gen2_pilot_dataset/data_provider/aria_gen2_pilot_data_paths.py
aria_gen2_pilot_dataset/data_provider/aria_gen2_pilot_data_paths_provider.py
aria_gen2_pilot_dataset/data_provider/aria_gen2_pilot_data_provider.py
aria_gen2_pilot_dataset/data_provider/aria_gen2_pilot_dataset_data_types.py
aria_gen2_pilot_dataset/data_provider/diarization_data_provider.py
aria_gen2_pilot_dataset/data_provider/egocentric_voxel_lifting_data_provider.py
aria_gen2_pilot_dataset/data_provider/hand_object_interaction_data_provider.py
aria_gen2_pilot_dataset/data_provider/heart_rate_data_provider.py
aria_gen2_pilot_dataset/data_provider/rle_utils.py
aria_gen2_pilot_dataset/data_provider/stereo_depth_data_provider.py
aria_gen2_pilot_dataset/data_provider/utils.py
aria_gen2_pilot_dataset/visualization/__init__.py
aria_gen2_pilot_dataset/visualization/aria_gen2_pilot_data_visualizer.py
aria_gen2_pilot_dataset/visualization/aria_gen2_pilot_dataset_viewer.py
aria_gen2_pilot_dataset/visualization/aria_gen2_pilot_viewer_config.py
aria_gen2_pilot_dataset/visualization/plot_color.py
aria_gen2_pilot_dataset/visualization/plot_style.py
aria_gen2_pilot_dataset/visualization/plot_utils.py
projectaria_gen2_pilot_dataset-1.0.0.dist-info/licenses/LICENSE
projectaria_gen2_pilot_dataset-1.0.0.dist-info/METADATA
projectaria_gen2_pilot_dataset-1.0.0.dist-info/WHEEL
projectaria_gen2_pilot_dataset-1.0.0.dist-info/entry_points.txt
projectaria_gen2_pilot_dataset-1.0.0.dist-info/top_level.txt
projectaria_gen2_pilot_dataset-1.0.0.dist-info/RECORD
