Metadata-Version: 2.4
Name: projectaria-gen2-pilot-dataset
Version: 1.0.0
Summary: Aria Gen2 Pilot Dataset
Home-page: https://github.com/facebookresearch/projectaria_gen2_pilot_dataset
Author: Meta Reality Labs Research
License: CC BY-NC 4.0
Classifier: Intended Audience :: Developers
Classifier: Intended Audience :: Science/Research
Classifier: Operating System :: OS Independent
Classifier: Programming Language :: Python :: 3.8
Classifier: Programming Language :: Python :: 3.9
Classifier: Programming Language :: Python :: 3.10
Classifier: Programming Language :: Python :: 3.11
Classifier: Programming Language :: Python :: 3.12
Classifier: Topic :: Scientific/Engineering
Classifier: Topic :: Scientific/Engineering :: Artificial Intelligence
Classifier: Topic :: Scientific/Engineering :: Image Processing
Classifier: Topic :: Multimedia :: Video
Requires-Python: >=3.8
License-File: LICENSE
Requires-Dist: projectaria-tools==2.0.0
Requires-Dist: pillow
Provides-Extra: all
Requires-Dist: jupyter; extra == "all"
Requires-Dist: rerun-notebook==0.22.1; extra == "all"
Dynamic: author
Dynamic: classifier
Dynamic: description
Dynamic: home-page
Dynamic: license
Dynamic: license-file
Dynamic: provides-extra
Dynamic: requires-dist
Dynamic: requires-python
Dynamic: summary
